qt_backport
PySide
PyQt4
