Metadata-Version: 1.1
Name: qt-backport
Version: 0.1.1
Summary: Makes PySide/PyQt4 code work with Qt5 (using PyQt5)
Home-page: https://github.com/rwarren/qt_backport
Author: Russell Warren
Author-email: russ@perspexis.com
License: MIT
Keywords: Qt PyQt4 PyQt5 PySide
Platform: UNKNOWN
Classifier: Development Status :: 3 - Alpha
Classifier: Intended Audience :: Developers
Classifier: Topic :: Software Development
Classifier: Topic :: Software Development :: User Interfaces
Classifier: Topic :: Software Development :: Libraries :: Python Modules
Classifier: License :: OSI Approved :: MIT License
Classifier: Programming Language :: Python
Classifier: Programming Language :: Python :: 2.6
Classifier: Programming Language :: Python :: 2.7
Classifier: Operating System :: OS Independent
